pyams_auth_jwt/__init__.py
pyams_auth_jwt/client.py
pyams_auth_jwt/include.py
pyams_auth_jwt/interfaces.py
pyams_auth_jwt/plugin.py
pyams_auth_jwt/proxy.py
pyams_auth_jwt/api/__init__.py
pyams_auth_jwt/doctests/README.rst
pyams_auth_jwt/generations/__init__.py
pyams_auth_jwt/generations/evolve1.py
pyams_auth_jwt/locales/pyams_auth_jwt.pot
pyams_auth_jwt/locales/fr/LC_MESSAGES/pyams_auth_jwt.mo
pyams_auth_jwt/locales/fr/LC_MESSAGES/pyams_auth_jwt.po
pyams_auth_jwt/tests/__init__.py
pyams_auth_jwt/tests/test_utilsdocs.py
pyams_auth_jwt/tests/test_utilsdocstrings.py
pyams_auth_jwt/zmi/__init__.py
pyams_auth_jwt/zmi/container.py
pyams_auth_jwt/zmi/interfaces.py
pyams_auth_jwt/zmi/plugin.py
pyams_auth_jwt-2.2.1.dist-info/LICENSE
pyams_auth_jwt-2.2.1.dist-info/METADATA
pyams_auth_jwt-2.2.1.dist-info/WHEEL
pyams_auth_jwt-2.2.1.dist-info/namespace_packages.txt
pyams_auth_jwt-2.2.1.dist-info/top_level.txt
pyams_auth_jwt-2.2.1.dist-info/RECORD
